spikenode.py
spikenode-0.1.3.dist-info/DESCRIPTION.rst
spikenode-0.1.3.dist-info/RECORD
spikenode-0.1.3.dist-info/top_level.txt
spikenode-0.1.3.dist-info/metadata.json
spikenode-0.1.3.dist-info/METADATA
spikenode-0.1.3.dist-info/entry_points.txt
spikenode-0.1.3.dist-info/WHEEL
