Metadata-Version: 2.0
Name: spikenode
Version: 0.1.3
Summary: SpikeNode Toolbelt
Home-page: https://github.com/spikenode/toolbelt
Author: Allan Denot
Author-email: allan.denot@spikenode.com
License: MIT
Keywords: spikenode devops ansible
Platform: UNKNOWN
Classifier: Development Status :: 4 - Beta
Classifier: Intended Audience :: Developers
Classifier: Natural Language :: English
Classifier: License :: OSI Approved :: MIT License
Classifier: Programming Language :: Python
Classifier: Programming Language :: Python :: 2.6
Classifier: Programming Language :: Python :: 2.7
Requires-Dist: requests (>=2.7.0)
Requires-Dist: pyopenssl
Requires-Dist: ndg-httpsclient
Requires-Dist: pyasn1
Requires-Dist: urllib3
